openstackinabox/__init__.py
openstackinabox/manager.py
openstackinabox/models/__init__.py
openstackinabox/models/base_db.py
openstackinabox/models/base_model.py
openstackinabox/models/cinder/__init__.py
openstackinabox/models/cinder/model.py
openstackinabox/models/keystone/__init__.py
openstackinabox/models/keystone/exceptions.py
openstackinabox/models/keystone/model.py
openstackinabox/models/keystone/db/__init__.py
openstackinabox/models/keystone/db/base.py
openstackinabox/models/keystone/db/endpoints.py
openstackinabox/models/keystone/db/roles.py
openstackinabox/models/keystone/db/services.py
openstackinabox/models/keystone/db/tenants.py
openstackinabox/models/keystone/db/tokens.py
openstackinabox/models/keystone/db/users.py
openstackinabox/models/swift/__init__.py
openstackinabox/models/swift/exceptions.py
openstackinabox/models/swift/model.py
openstackinabox/models/swift/storage.py
openstackinabox/services/__init__.py
openstackinabox/services/base_service.py
openstackinabox/services/cinder/__init__.py
openstackinabox/services/cinder/v1/__init__.py
openstackinabox/services/cinder/v1/base.py
openstackinabox/services/cinder/v1/volumes.py
openstackinabox/services/keystone/__init__.py
openstackinabox/services/keystone/v2/__init__.py
openstackinabox/services/keystone/v2/base.py
openstackinabox/services/keystone/v2/exceptions.py
openstackinabox/services/keystone/v2/tenants.py
openstackinabox/services/keystone/v2/tokens.py
openstackinabox/services/keystone/v2/users.py
openstackinabox/services/swift/__init__.py
openstackinabox/services/swift/v1/__init__.py
openstackinabox/tests/__init__.py
openstackinabox/tests/base.py
openstackinabox/tests/test_manager.py
openstackinabox/tests/models/__init__.py
openstackinabox/tests/models/test_base.py
openstackinabox/tests/models/cinder/__init__.py
openstackinabox/tests/models/cinder/test_model.py
openstackinabox/tests/models/db/__init__.py
openstackinabox/tests/models/db/test_base.py
openstackinabox/tests/models/keystone/__init__.py
openstackinabox-0.2.dist-info/LICENSE
openstackinabox-0.2.dist-info/METADATA
openstackinabox-0.2.dist-info/WHEEL
openstackinabox-0.2.dist-info/top_level.txt
openstackinabox-0.2.dist-info/zip-safe
openstackinabox-0.2.dist-info/RECORD
