Metadata-Version: 2.1
Name: openstackinabox
Version: 0.2
Summary: OpenStack APIs for the Stack-In-A-Box Testing Suite
Home-page: https://github.com/TestInABox/openstackinabox
Author: Benjamen R. Meyer
Author-email: bm_witness@yahoo.com
License: Apache License 2.0
Classifier: Intended Audience :: Developers
Classifier: License :: OSI Approved :: Apache Software License
Classifier: Topic :: Software Development :: Testing
License-File: LICENSE
Requires-Dist: six
Requires-Dist: stackinabox >=0.13
